{
  "music": [
    "Asia New Beat亚洲独立音乐大赛将于2026年5月30-31日在马来西亚举办，16组亚洲独立音乐人阵容已公布，由HLB Visa卡和JOOX联合呈现。",
    "Orcutt Shelley Miller乐队巡演七寸单曲正式发售，A面《Hot Head》由David Yow献唱，B面《A Man Needs A Maid》由Ethan演绎。",
    "EmptyORio乐队以专辑为主题完成8场全台巡演，从北到南覆盖多个城市，有日本、香港歌迷专程飞往现场。",
    "凯文怎么了？影片将于2026年6月12日至28日在国家电影及视听文化中心大影格放映，片长112分钟，级别为辅12级。",
    "马来西亚芙蓉中华中学将于5月30日举办《聚驹6.0》音乐会，200多名乐手同台演绎Beyond作品，筹款用于学校建校基金。",
    "ACN Newswire提供多语种新闻稿发布服务，支持英文、简体中文、繁体中文、韩文和日文，面向媒体和金融市场。",
    "UCLA儿科内分泌与代谢专科医师培训项目开放申请，提供临床和学术培训，满足美国儿科学会专科认证要求。",
    "香港天安门纪念活动组织者李卓人和邹幸彤的国安法案件进入最后陈述阶段，法庭于5月18日进行审理。",
    "音乐人郭峰62岁未婚，创作千首作品，从冬奥到亚冬持续活跃，其1980年代作品《让世界充满爱》影响力延续近四十年。",
    "Blow吹音乐报道：EmptyORio乐队主唱ORio透露，巡演第二场起便出现日本和香港歌迷跨海追随。"
  ],
  "novel": [
    "台湾作家杨双子以小说《臺湾漫游录》入围布克奖决选名单，成为本届唯一来自亚洲的作家，也刷新了台湾作家在该奖项的纪录。布克奖将于5月19日公布得主。",
    "杨双子的《臺湾漫游录》聚焦台湾美食与殖民记忆，凭借独特叙事入围布克奖。该奖是英国最具指标的文学奖之一。",
    "第七届谢璞儿童文学奖在长沙启动，旨在纪念作家谢璞，促进短篇儿童文学创作，为少年儿童提供优质精神食粮。",
    "研究小组以日本小说家星新一的作品及星新一文学奖获奖作品为样本，让人工智能参与小说创作，挑战该文学奖的征集活动。",
    "莫言除诺贝尔文学奖外，还曾获茅盾文学奖、华语文学传媒大奖·年度杰出成就奖、世界华文长篇小说奖·红楼梦奖等国内外文学大奖。",
    "上海交通大学高级工程师王一超获校“管理服务奖”一等奖，曾获评“三大卓越奖励计划”实验系列及中国计算机学会高性能计算学术奖。",
    "茅盾文学奖得主周大新代表作《21大厦》探讨都市秘密、人性与财富，以保安视角揭示社会现实。作品被改编为中文有声书。",
    "根据《中华人民共和国著作权法》第四十八条，侵权人需按权利人实际损失或违法所得赔偿著作权侵权行为；难以计算的，可适用法定赔偿。",
    "诺贝尔文学奖得主作品包括克拉斯诺霍尔卡伊·拉斯洛的《反抗的忧郁》《仁慈的关系》，以及韩江的《素食者》《白》《植物妻子》。",
    "TWNIC致力于共创开放及安全的网络连接，服务涵盖域名服务、IP/ASN、网络安全及社群培力，以链接全球数字未来。"
  ],
  "tech": [
    "太保蓝公益首个“AI未来星工坊”在上海启动，项目采用“特殊教育+职业教育”融合模式，借助AI技术赋能特殊儿童成长，上海市民政局副局长娄国剑出席活动。",
    "纵行科技因在工业设备预测性维护领域的合作，获颁施耐德电气“EAE精英伙伴最佳合作奖”，双方联合方案EcoPredict推动设备管理从被动维护转向主动预测。",
    "大众汽车集团在2026北京车展前夕举办媒体之夜，携四款全球首秀车型亮相，并宣布全域智能体AI正式落地。",
    "一项基于2000位用户和100家企业管理者的调查显示，开源项目OpenClaw（“龙虾”）两周内用户流失率接近七成，尽管用户初期投入硬件和月费的热情较高。",
    "美国SEEQC公司与中国台湾工研院达成合作，将共建先进超导电子控制芯片生产线，相关新闻发布于2025年12月8日。",
    "美国联合研究团队制造出首颗单片3D芯片，性能提升约4倍，相关突破报道于2025年11月26日发布。",
    "重庆大足区出现涉及色情服务的招聘信息，招聘平台LinkedIn上包含此类违规内容，需注意信息审核。",
    "软件技术专业省级产业导师联袂召开AI前沿技术讲座，活动于2024年7月5日在智能工程学院举办。",
    "closerAI平台上线，专注提供前沿人工智能与AIGC领域资讯，包括AI绘画教程、ComfyUI工作流及节点知识。",
    "B站于2026年5月17日收录一批AI新内容，涵盖前沿观点、技术与商业范式，每条均附权威来源及可访问链接。"
  ],
  "movie": [
    "谢文明动画短片辑《谢文明动画短片辑》在公视+平台免费上线，该片曾二度获得金马奖最佳动画，并入围日舞、安锡等国际影展。",
    "第11届戛纳电影节获奖名单公布，《雁南飞》获金棕榈奖，英格玛·伯格曼凭《生命的门槛》获最佳导演，该片四位女演员共享最佳女演员奖。",
    "翔宇教育集团投拍的电影《锦绣花园》在洛杉矶国际电影节获奖，该片由集团制作，具体奖项未披露。",
    "吉姆·贾木许将禅学经典《禅与饮茶的艺术》改编为电影《幽灵狗：忍者之路》，该片于1999年全球上映，贾木许深谙东方哲学并曾翻译《道德经》。"
  ],
  "focus": [
    "自3月以来，多架乌克兰无人机进入拉脱维亚、立陶宛和爱沙尼亚领空，这些国家均为北约成员国，与俄罗斯及其盟友白俄罗斯接壤。",
    "俄罗斯总统普京将于周二对中国进行国事访问，同日伊朗股市重开，英国失业率与美国ADP就业数据将公布。",
    "中国一年期贷款市场报价利率将于周三公布，同日SpaceX有星链任务。",
    "美国能源部长表示，霍尔木兹海峡最迟今夏将重新开放。",
    "以色列大规模空袭黎巴嫩南部，并称击杀一名哈马斯行动总部指挥官；阿联酋巴拉卡核电站外围发电机遭无人机袭击。",
    "美国4月CPI与PPI因能源价格上涨高于预期，推高美债收益率，市场重燃升息预期。",
    "2026年5月15日，特朗普结束访华行程后，中美经贸磋商取得初步成果，中国商务部发布相关声明。",
    "2026年世界杯转播权正式落地中国，《足球报》指出这不仅是中国需要世界杯，世界杯也需要中国市场。",
    "地缘冲突加剧使布伦特原油一度突破110美元/桶，过去一周（5月11日至17日）全球紧张局势升级。",
    "北京欧中论坛上，欧盟与中国外交官因贸易问题发生激烈争执，双方互批保护主义与霸凌。"
  ],
  "lastUpdated": "2026-05-18T19:45:38.825Z"
}