{
  "music": [
    "Orcutt Shelley Miller 巡演七寸单曲正式面世并现场售卖，A 面为 David Yow 献唱的《Hot Head》，B 面为 Ethan 演绎的《A Man Needs A Maid》。",
    "鄭宜農專輯《圓缺》橫掃金曲獎多項提名，她人還在國外巡演，尚未回台慶祝。",
    "《歌手2026》官宣首发阵容，齐豫、庾澄庆领衔，共9位歌手包括老牌前辈、实力唱将、新生代及海外歌手。",
    "王新也发布歌曲《马斯克不会不好意思》，描述像在机场VIP室突然演讲，次日新闻头条全是他。",
    "专辑从身体里长出来，包含10首歌如《苹果上的豹》《北京》，涵盖天性、成长、反叛与信仰。",
    "LBI利比本名石白尘，是中国男歌手、词曲作者及音乐制作人，其演唱会在MYFM推荐中强调不能少了《或许》。",
    "胡彦斌在《歌手2026》5月22日的表演回归舞台，被视为对即兴创作价值的平反和技术流音乐人的加冕。",
    "中国全能音乐人小鬼王琳凯携专辑《魁》在吉隆坡开启海外首演，出道8年与“5年网友”NYK奔现合体告白。",
    "《聚驹6.0》走进校园，主办方表示Beyond作品从小朋友到老人都耳熟能详，不止是演唱会更有意义。",
    "2026年5月29日至6月7日，城市副中心绿心森林音乐节将在北京艺术中心绿心露天剧场举办，由国家大剧院主办。"
  ],
  "novel": [
    "莫言成为首位获得诺贝尔文学奖的中国籍作家，瑞典文学院称其作品融合魔幻现实主义与民间故事。2012年10月11日，他凭借《红高粱》等作品获奖。",
    "第七届谢璞儿童文学奖在长沙启动，该奖项旨在纪念作家谢璞并促进短篇儿童文学创作，由中国寓言文学研究会等机构主办。",
    "第一届广西青年文学奖评选结果揭晓，小昌长篇小说《海雾弥漫》获最高奖，显示新一代广西青年作家文学影响力上升。",
    "诺贝尔文学奖得主莫言在视频中谈论‘人生只有一次’，分享《生死疲劳》等作品背后的人生感悟，引发关注。",
    "豫论场评论指出网络信息易失真，呼吁公众在看到耸人听闻的关联信息时先核实来源，以减少误伤。",
    "莫言获诺贝尔文学奖后，中国各地民众欢欣鼓舞，其作品生动刻画中国近现代史人物生存形态，获高度评价。",
    "《文学城》新书多角度记述十余位与诺贝尔文学奖有关作家的创作历程，揭秘评奖历史故事。",
    "韩国作家金爱烂的短篇小说集《你的夏天还好吗？》曾获《韩国日报》文学奖、李箱文学奖等多项大奖。",
    "第九届茅盾文学奖得主李佩甫的短作品精选集《离我们很近》收录《学习微笑》《满城荷花》等经典篇目。",
    "上海交通大学高级工程师王一超因高性能计算服务获校‘管理服务奖’一等奖，曾获中国计算机学会奖项。"
  ],
  "tech": [
    "200集李沐人工智能课程合集发布，涵盖动手学深度学习、实用机器学习、AI论文精读及OpenCV图像识别，获6.7万次观看。",
    "WorkBuddy自动化实战记录每日市场情报推送搭建过程，涉及QQ邮箱MCP双步确认、HTML邮件发送及Prompt精简等踩坑点。",
    "closerAI上线，定位为深入探索人工智能与AIGC领域的信息平台，提供科技资讯、AI绘画教程、ComfyUI工作流及节点知识。",
    "深圳博物馆展览工作部青年设计师刘永芳论文入选2026年学术会议，体现AI赋能文化传播领域的研究成果。",
    "大众汽车集团在2026北京车展前夜举行媒体之夜，携四款全球首秀车型及全域智能体AI技术亮相。",
    "移远通信在CES推出'物理AI'概念，通过算法超市与一站式工具链让开发者像逛超市一样选择AI能力。",
    "5月9日上海龙虾会技术沙龙聚焦AI前沿，主题包括尝鲜文化、AI员工生态建设及OPC/OPT开放标准赋能。",
    "太保蓝公益'AI未来星工坊'在上海启动，以AI技术结合'特殊教育+职业教育'模式赋能特殊儿童成长。",
    "武汉市率先搭建'无障碍报警系统'，利用AI技术为听力、言语障碍人士提供110、119、120、122一键求助服务。",
    "武汉市残联将多部门报警系统整合至AI平台，系统性破解残障群体紧急求助难题。"
  ],
  "movie": [
    "第55届卡罗维发利国际电影节获奖名单公布，《雅库特的春天》获7.7分，《零秒出手：悬崖上的英雄》7.7分，《黑道看护》8分，《救命病栋24小时第4季》7.7分，《官僚们的夏天》8.3分。",
    "第28届上海国际电影节金爵奖亚洲新人单元评委会阵容揭晓，新加坡导演陈哲艺担任主席，印度尼西亚导演卡米拉·安担任委员。",
    "第44届报知映画赏获奖名单发布，《我这样过了一生》8.3分，《等待黎明》获奖；第49届法国凯撒电影奖中《坠落的审判》8.7分，《戈德曼审判》获奖。",
    "台湾动画导演谢文明的短片合集在日舞、安锡等国际影展获奖或入围，其作品以剪纸动画为特色，目前可在公视+免费收看。",
    "第3届戛纳电影节获奖名单中《北方一片苍茫》6.7分，《妮娜》7分，《罪人》7.5分；第73届柏林国际电影节中《坚毅之旅》6.7分，《蛹》7.5分，《红色天空》7.6分。",
    "第7届华语电影传媒大奖获奖名单公布，《行骗天下JP：浪漫篇》8.1分；第54届卡罗维发利国际电影节中《错会半生》7.7分，《帕特里克》6.4分，《八月处子》7.5分。",
    "艺术影院不以票房为目标，专注展映实验电影、国际电影节获奖影片及经典黑白电影，在商业浪潮中坚守文化灵魂。",
    "翔宇教育集团投拍的电影《锦绣花园》在洛杉矶国际电影节获奖，该片由集团出品。",
    "导演莫少琳的作品《暗涌》和《镜中人》获多项国际电影节大奖，其电影探索生命、记忆与身份主题。",
    "2023年电影《光的背面》聚焦单亲妈妈群体的生存困境与精神成长，斩获多项国际电影节大奖，并在社交媒体引发讨论。"
  ],
  "focus": [
    "美能源部长表示，霍尔木兹海峡最迟今夏重开，中东局势或迎转折。美国已部署15艘军舰封锁伊朗港口，以色列24小时内空袭黎巴嫩南部并清剿200个真主党目标，阿联酋巴拉卡核电站外围发电机遭无人机袭击。",
    "普京在别墅周围部署26套防空系统，俄经济面临699亿美元赤字压力。乌军使用火烈鸟导弹猛攻喀山等地并摧毁S300防空系统，俄军防线出现结构性崩溃迹象。",
    "乌克兰无人机自3月以来多次进入拉脱维亚、立陶宛和爱沙尼亚领空，引发北约成员国关注。俄乌边境紧张局势持续升级。",
    "中美元首会晤后，中国商务部确认双方就关税安排形成积极共识，同意成立贸易理事会。特朗普预计于美东时间下午4:30就美中关系发表声明，内部人士称其将宣布中国对美投资1万亿美元。",
    "柬埔寨移民局于5月14日至16日将457名涉嫌网络诈骗的中国和越南公民遣返，行动由副首相兼内政部长指示。",
    "伊朗最强硬的两名代表与美国进行谈判，但美国副总统万斯的介入被认为帮了倒忙。美军15艘军舰封锁伊朗港口，切断其海上生命线。",
    "以色列称袭杀哈马斯行动总部一名指挥官，并在24小时内对真主党200个目标实施轰炸。中东多国军事行动持续加剧。",
    "俄罗斯合同兵出现出逃现象，征兵数量大幅锐减。俄军前线指挥官虐待士兵的丑闻被曝光，进一步影响部队士气。",
    "乌克兰在太空领域取得突破，配合地面攻势打击俄方纵深目标。俄军S300防空系统在喀山等地被乌军摧毁。",
    "特朗普批评教皇软弱无能，匈牙利欧尔班政府遭遇惨败。国际政治格局多处失衡，各方博弈进入新阶段。"
  ],
  "lastUpdated": "2026-05-18T08:05:04.814Z"
}